README.md
setup.cfg
setup.py
fastqp/__init__.py
fastqp/adapters.py
fastqp/cli.py
fastqp/plots.py
fastqp.egg-info/PKG-INFO
fastqp.egg-info/SOURCES.txt
fastqp.egg-info/dependency_links.txt
fastqp.egg-info/entry_points.txt
fastqp.egg-info/requires.txt
fastqp.egg-info/top_level.txt
fastqp/backports/__init__.py