Metadata-Version: 1.1
Name: fastqp
Version: 0.3.3
Summary: Simple NGS read quality assessment using Python
Home-page: http://mattshirley.com
Author: Matthew Shirley
Author-email: mdshw5@gmail.com
License: MIT
Platform: UNKNOWN
Classifier: Development Status :: 5 - Production/Stable
Classifier: License :: OSI Approved :: MIT License
Classifier: Environment :: Console
Classifier: Intended Audience :: Science/Research
Classifier: Natural Language :: English
Classifier: Operating System :: Unix
Classifier: Programming Language :: Python :: 2.7
Classifier: Programming Language :: Python :: 3.6
Classifier: Topic :: Scientific/Engineering :: Bio-Informatics
Provides: f
Provides: a
Provides: s
Provides: t
Provides: q
Provides: p
